call_serverless/__init__.py
call_serverless/apis.py
call_serverless/exceptions.py
call_serverless/formatter.py
call_serverless/py.typed
call_serverless/response.py
call_serverless/template.py
call_serverless-0.2.9.dist-info/licenses/LICENSE
call_serverless-0.2.9.dist-info/METADATA
call_serverless-0.2.9.dist-info/WHEEL
call_serverless-0.2.9.dist-info/top_level.txt
call_serverless-0.2.9.dist-info/RECORD
