Metadata-Version: 2.4
Name: call-serverless
Version: 0.2.9
Summary: Remote call AWS Lambda functions directly that have API Gateway integration
Home-page: https://github.com/er-nabin-bhusal/call-serverless
Author: Nabin Bhusal
Author-email: nabinbhusal80@gmail.com
License: MIT
Classifier: Programming Language :: Python :: 3
Classifier: License :: OSI Approved :: MIT License
Classifier: Operating System :: OS Independent
Requires-Python: >=3.8
License-File: LICENSE
Requires-Dist: boto3
Requires-Dist: aiobotocore
Dynamic: author
Dynamic: author-email
Dynamic: classifier
Dynamic: description
Dynamic: description-content-type
Dynamic: home-page
Dynamic: license
Dynamic: license-file
Dynamic: requires-dist
Dynamic: requires-python
Dynamic: summary
